islucky/__init__.py
islucky/is_equal.py
islucky-0.1.0.dist-info/METADATA
islucky-0.1.0.dist-info/WHEEL
islucky-0.1.0.dist-info/top_level.txt
islucky-0.1.0.dist-info/RECORD
